py2appsigner/ApplicationNotarize.py
py2appsigner/ApplicationSign.py
py2appsigner/ApplicationStaple.py
py2appsigner/ApplicationVerify.py
py2appsigner/BaseCommand.py
py2appsigner/CommandBasic.py
py2appsigner/CommandExtended.py
py2appsigner/Commands.py
py2appsigner/Common.py
py2appsigner/Notary.py
py2appsigner/ZipSign.py
py2appsigner/__init__.py
py2appsigner/_version.py
py2appsigner/environment/BasicEnvironment.py
py2appsigner/environment/Environment.py
py2appsigner/environment/NotaryEnvironment.py
py2appsigner/environment/__init__.py
py2appsigner/resources/__init__.py
py2appsigner/resources/loggingConfiguration.json
py2appsigner-0.6.95.dist-info/licenses/LICENSE
py2appsigner-0.6.95.dist-info/METADATA
py2appsigner-0.6.95.dist-info/WHEEL
py2appsigner-0.6.95.dist-info/entry_points.txt
py2appsigner-0.6.95.dist-info/top_level.txt
py2appsigner-0.6.95.dist-info/RECORD
