Metadata-Version: 2.4
Name: py2appsigner
Version: 0.6.95
Summary: Scripts to Code Sign py2app applications
Author-email: "Humberto A. Sanchez II" <Humbert.A.Sanchez.II@gmail.com>
Maintainer-email: "Humberto A. Sanchez II" <Humbert.A.Sanchez.II@gmail.com>
License-Expression: AGPL-1.0-or-later
Project-URL: Repository, https://github.com/hasii2011/py2appsigner
Keywords: code signing,py2app,python
License-File: LICENSE
Requires-Dist: tqdm>=4.67.1
Requires-Dist: click>=8.3.0
Provides-Extra: test
Requires-Dist: mypy==1.18.2; extra == "test"
Requires-Dist: mypy-extensions==1.1.0; extra == "test"
Requires-Dist: html-testRunner==1.2.1; extra == "test"
Requires-Dist: codeallybasic==1.30.0; extra == "test"
Provides-Extra: deploy
Requires-Dist: wheel==0.45.1; extra == "deploy"
Requires-Dist: setuptools==80.9.0; extra == "deploy"
Requires-Dist: twine==6.2.0; extra == "deploy"
Requires-Dist: build==1.2.2.post1; extra == "deploy"
Dynamic: license-file
